{
  "code": "AID",
  "title": "Accountability: Federal Accountability Standards",
  "description": "Federal accountability standards require Conroe ISD to measure and report how well students are learning and how effectively schools are performing. The district uses this data to identify schools that may need additional support and to ensure all students, including those from different backgrounds and learning needs, are making progress. Parents and community members can use this information to better understand how their local schools are performing and what steps are being taken to improve outcomes.",
  "policy_connect_url": "https://policyconnect.org/policy/conroe-isd/AID",
  "last_action_date": null,
  "last_action_result": null,
  "timeline_local": [],
  "timeline_legal": []
}