{
  "code": "BHC",
  "title": "Suspension of Policies",
  "description": "The Board of Trustees has the authority to temporarily set aside certain district policies when unusual or unique circumstances make it necessary to do so. Suspending a policy requires approval from the full board and can only happen when no state or federal law would be violated. This process helps ensure the district can respond flexibly to unexpected situations while still maintaining accountability and legal compliance.",
  "policy_connect_url": "https://policyconnect.org/policy/conroe-isd/BHC",
  "last_action_date": null,
  "last_action_result": null,
  "timeline": []
}