{
  "code": "DCD",
  "title": "Employment Practices: At-Will Employment",
  "description": "This policy governs the at-will employment relationship between the organization and its employees. It establishes that employment is not guaranteed for any set period of time and can be ended by either the employer or the employee at any time. The policy defines the terms and conditions under which this at-will status applies across the organization.",
  "policy_connect_url": "https://policyconnect.org/policy/conroe-isd/DCD",
  "last_action_date": null,
  "last_action_result": null,
  "timeline_local": [],
  "timeline_legal": []
}