{
  "code": "DFBA",
  "title": "Term Contracts: Suspension/Termination During Contract",
  "description": "This policy governs the suspension or termination of employees who are under term contracts before those contracts have expired. It outlines the conditions and procedures that apply when employment is ended or paused mid-contract rather than at the conclusion of the agreed term.",
  "policy_connect_url": "https://policyconnect.org/policy/conroe-isd/DFBA",
  "last_action_date": null,
  "last_action_result": null,
  "timeline_local": [],
  "timeline_legal": []
}