{
  "code": "EHBAB",
  "title": "Special Education: ARD Committee and Individualized Education Program",
  "description": "This policy governs the operation of the Admission, Review, and Dismissal (ARD) committee and the development of Individualized Education Programs (IEPs) for students who receive special education services. It outlines the structure, responsibilities, and decision-making processes of the ARD committee in relation to identifying and serving students with disabilities. The policy also addresses the requirements for creating, reviewing, and implementing IEPs in accordance with applicable education standards.",
  "policy_connect_url": "https://policyconnect.org/policy/conroe-isd/EHBAB",
  "last_action_date": null,
  "last_action_result": null,
  "timeline_local": [],
  "timeline_legal": []
}