{
  "code": "EK",
  "title": "Testing Programs",
  "description": "Policy EK addresses the use of testing programs within a school district. It covers the administration, oversight, and purpose of various assessments given to students, including standardized and locally developed tests. The policy establishes the framework for how testing is conducted and managed across the district.",
  "policy_connect_url": "https://policyconnect.org/policy/conroe-isd/EK",
  "last_action_date": null,
  "last_action_result": null,
  "timeline_local": [],
  "timeline_legal": []
}