{
  "code": "FEB",
  "title": "Attendance: Attendance Accounting",
  "description": "This policy governs how student attendance is recorded and tracked within a school or district. It establishes the procedures and standards used to account for student presence, absence, and tardiness. The policy outlines the framework for maintaining accurate attendance records in compliance with applicable requirements.",
  "policy_connect_url": "https://policyconnect.org/policy/conroe-isd/FEB",
  "last_action_date": null,
  "last_action_result": null,
  "timeline_local": [],
  "timeline_legal": []
}