{
  "code": "FFF",
  "title": "Student Welfare: Student Safety",
  "description": "Policy FFF addresses the safety and well-being of students within the school environment. It covers the responsibilities and procedures related to protecting students from harm, whether physical, emotional, or otherwise, while they are under the school's care. This policy governs the measures and expectations in place to maintain a secure setting for students.",
  "policy_connect_url": "https://policyconnect.org/policy/conroe-isd/FFF",
  "last_action_date": null,
  "last_action_result": null,
  "timeline_local": [],
  "timeline_legal": []
}