{
  "code": "FNCA",
  "title": "Student Conduct: Dress Code",
  "description": "Conroe ISD's dress code policy sets the standards for how students are expected to dress while at school and school-related activities. It outlines what clothing, accessories, and styles of dress are and are not permitted on campuses. Parents and students can refer to this policy to understand the district's expectations and help avoid disruptions to the learning environment.",
  "policy_connect_url": "https://policyconnect.org/policy/conroe-isd/FNCA",
  "last_action_date": null,
  "last_action_result": null,
  "timeline_local": [],
  "timeline_legal": []
}